odoo/addons/website_sale_exception/README.rst
odoo/addons/website_sale_exception/__init__.py
odoo/addons/website_sale_exception/__manifest__.py
odoo/addons/website_sale_exception/i18n/ca.po
odoo/addons/website_sale_exception/i18n/es.po
odoo/addons/website_sale_exception/i18n/fr.po
odoo/addons/website_sale_exception/i18n/nl.po
odoo/addons/website_sale_exception/i18n/website_sale_exception.pot
odoo/addons/website_sale_exception/models/__init__.py
odoo/addons/website_sale_exception/models/sale.py
odoo/addons/website_sale_exception/readme/CONTRIBUTORS.rst
odoo/addons/website_sale_exception/readme/DESCRIPTION.rst
odoo/addons/website_sale_exception/static/description/icon.png
odoo/addons/website_sale_exception/static/description/index.html
odoo12_addon_website_sale_exception-12.0.1.0.0.99.dev13.dist-info/METADATA
odoo12_addon_website_sale_exception-12.0.1.0.0.99.dev13.dist-info/WHEEL
odoo12_addon_website_sale_exception-12.0.1.0.0.99.dev13.dist-info/top_level.txt
odoo12_addon_website_sale_exception-12.0.1.0.0.99.dev13.dist-info/RECORD
